joust/__init__.py
joust/__main__.py
joust/config.py
joust/protocol.py
joust/redis.py
joust/server.py
joust/session.py
joust/game/__init__.py
joust/game/channels.py
joust/game/game.py
joust/game/protocol.py
joust/match/__init__.py
joust/match/protocol.py
joust-1.0.0.dist-info/LICENSE
joust-1.0.0.dist-info/METADATA
joust-1.0.0.dist-info/WHEEL
joust-1.0.0.dist-info/entry_points.txt
joust-1.0.0.dist-info/top_level.txt
joust-1.0.0.dist-info/RECORD
